nicholasbruce/main.py
nicholasbruce-0.0.0.dist-info/METADATA
nicholasbruce-0.0.0.dist-info/WHEEL
nicholasbruce-0.0.0.dist-info/entry_points.txt
nicholasbruce-0.0.0.dist-info/top_level.txt
nicholasbruce-0.0.0.dist-info/RECORD
