Metadata-Version: 2.4
Name: nicholasbruce
Version: 0.0.0
Summary: Nicholas Bruce's terminal business card
Requires-Python: >=3.12
Requires-Dist: termcolor>=3.1.0
